cscart/__init__.py
cscart/client.py
cscart_api_client-0.1.0.dist-info/LICENSE
cscart_api_client-0.1.0.dist-info/WHEEL
cscart_api_client-0.1.0.dist-info/METADATA
cscart_api_client-0.1.0.dist-info/RECORD
